{
  "require": [
    [
      "CometQPLPayloadStore",
      "storePayloadBytesSent",
      null,
      [
        {
          "htmlStart": [
            104447,
            14974
          ],
          "tierOne": [
            215741,
            53439
          ],
          "ssr_error": [
            389,
            49
          ],
          "adp_PolarisLoggedOutDesktopWWWProfileRootContentQueryRelayPreloader_{N}": [
            79936,
            13468
          ],
          "tierTwo": [
            126519,
            22948
          ],
          "adp_PolarisLoggedOutDesktopWWWProfilePostsTabContentQueryRelayPreloader_{N}": [
            16861,
            5156
          ],
          "tierThree": [
            116458,
            20977
          ],
          "adp_WebWorkerV2HasteResponsePreloader_ZenonSignalingSharedWorkerV2Bundle_{N}": [
            37254,
            1694
          ]
        }
      ]
    ]
  ]
}